{"cameraMode":{"drawMode":0,"name":"Shaded","section":"Shading Mode"},"sceneLighting":false,"audioPlay":false,"sceneViewState":{"m_AlwaysRefresh":false,"showFog":true,"showSkybox":false,"showFlares":true,"showImageEffects":true,"showParticleSystems":true,"showVisualEffectGraphs":true,"m_FxEnabled":true},"in2DMode":false,"pivot":{"x":-1.8476914167404175,"y":0.18746256828308106,"z":-16.002599716186525},"rotation":{"x":0.5038470029830933,"y":0.49603164196014407,"z":-0.507502555847168,"w":0.49249330163002016},"size":5.49111795425415,"orthographic":false}